where2Go-0.0.4.dist-info/RECORD
where2Go-0.0.4.dist-info/top_level.txt
where2Go-0.0.4.dist-info/METADATA
where2Go-0.0.4.dist-info/metadata.json
where2Go-0.0.4.dist-info/WHEEL
where2Go-0.0.4.dist-info/DESCRIPTION.rst
where2Go/landmark.py
where2Go/directions_and_durations.py
where2Go/landmarks.db
where2Go/db_and_forecast.py
where2Go/__init__.py
