Metadata-Version: 2.0
Name: where2Go
Version: 0.0.4
Summary: Your weekend-adventure assistant
Home-page: UNKNOWN
Author: Georgi Ivanov
Author-email: georgi.g.ivanov.95@gmail.com
License: GNU GPL v2
Keywords: weekend,walk,adventure,mountain,nature
Platform: UNKNOWN
Classifier: Development Status :: 3 - Alpha
Classifier: Intended Audience :: End Users/Desktop
Classifier: License :: OSI Approved :: GNU General Public License v2 (GPLv2)
Classifier: Natural Language :: English
Classifier: Operating System :: POSIX :: Linux
Classifier: Programming Language :: Python :: 3.5
Classifier: Topic :: Games/Entertainment
Requires-Dist: beautifulsoup4 (==4.4.1)
Requires-Dist: requests (==2.10.0)
